hf_video/__init__.py
hf_video/src/__init__.py
hf_video/src/byte_decoder.py
hf_video/src/data.py
hf_video/src/upload_data.py
hf_video/test/__init__.py
hf_video/test/test_hf_video.py
hf_video-0.0.2.dist-info/LICENSE
hf_video-0.0.2.dist-info/METADATA
hf_video-0.0.2.dist-info/WHEEL
hf_video-0.0.2.dist-info/top_level.txt
hf_video-0.0.2.dist-info/RECORD
